BubotObj/OcfDevice/subtype/ModbusMaster/ModbusMaster.json
BubotObj/OcfDevice/subtype/ModbusMaster/ModbusMaster.py
BubotObj/OcfDevice/subtype/ModbusMaster/__init__.py
BubotObj/OcfDevice/subtype/ModbusSlave/ModbusSlave.json
BubotObj/OcfDevice/subtype/ModbusSlave/ModbusSlave.py
BubotObj/OcfDevice/subtype/ModbusSlave/__init__.py
BubotObj/OcfDevice/subtype/SerialServerHF511/SerialServerHF511.json
BubotObj/OcfDevice/subtype/SerialServerHF511/SerialServerHF511.py
BubotObj/OcfDevice/subtype/SerialServerHF511/__init__.py
BubotObj/OcfSchema/schema/bubot.modbus.msg-schema.json
BubotObj/OcfSchema/schema/bubot.modbus.slave.con-schema.json
BubotObj/OcfSchema/schema/bubot.serial.con-schema.json
BubotObj/OcfSchema/schema/bubot.serialserver.con-schema.json
Bubot_Modbus-0.0.2.dist-info/LICENSE
Bubot_Modbus-0.0.2.dist-info/METADATA
Bubot_Modbus-0.0.2.dist-info/WHEEL
Bubot_Modbus-0.0.2.dist-info/top_level.txt
Bubot_Modbus-0.0.2.dist-info/RECORD
