Metadata-Version: 2.1
Name: Bubot-Modbus
Version: 0.0.2
Summary: IoT OCF Modbus bridge
Home-page: https://github.com/businka/Bubot_Modbus
Author: Razgovorov Mikhail
Author-email: 1338833@gmail.com
License: UNKNOWN
Platform: UNKNOWN
Classifier: Programming Language :: Python :: 3
Classifier: License :: OSI Approved :: MIT License
Classifier: Operating System :: OS Independent
Classifier: Development Status :: 3 - Alpha
Classifier: Framework :: AsyncIO
Requires-Python: >=3.7
Requires-Dist: Bubot-Core
Requires-Dist: aio-modbus-client
